mux_2to1.v
module mux_2to1 (
    input wire a,    
    input wire b,    
    input wire sel,   
    output wire y     
);
    assign y = sel ? b : a;
endmodule

module testbench;
    reg a, b, sel;
    wire y;

    mux_2to1 uut (
        .a(a),
        .b(b),
        .sel(sel),
        .y(y)
    );

    initial begin
        $dumpfile("test1.vcd");
        $dumpvars(0, testbench);
        
        $display("sel | a | b | y"); 
        $display("----------------");

        a = 0; b = 0; sel = 0; #10; $display("  %b  | %b | %b | %b", sel, a, b, y);
        a = 0; b = 1; sel = 0; #10; $display("  %b  | %b | %b | %b", sel, a, b, y);
        a = 1; b = 0; sel = 0; #10; $display("  %b  | %b | %b | %b", sel, a, b, y);
        a = 1; b = 1; sel = 0; #10; $display("  %b  | %b | %b | %b", sel, a, b, y);
        a = 0; b = 0; sel = 1; #10; $display("  %b  | %b | %b | %b", sel, a, b, y);
        a = 0; b = 1; sel = 1; #10; $display("  %b  | %b | %b | %b", sel, a, b, y);
        a = 1; b = 0; sel = 1; #10; $display("  %b  | %b | %b | %b", sel, a, b, y);
        a = 1; b = 1; sel = 1; #10; $display("  %b  | %b | %b | %b", sel, a, b, y);
        
        $finish;
    end
endmodule

test1.vcd
$date
	Fri Feb 28 13:36:44 2025
$end
$version
	Icarus Verilog
$end
$timescale
	1s
$end
$scope module testbench $end
$var wire 1 ! y $end
$var reg 1 " a $end
$var reg 1 # b $end
$var reg 1 $ sel $end
$scope module uut $end
$var wire 1 " a $end
$var wire 1 # b $end
$var wire 1 $ sel $end
$var wire 1 ! y $end
$upscope $end
$upscope $end
$enddefinitions $end
$comment Show the parameter values. $end
$dumpall
$end
#0
$dumpvars
0$
0#
0"
0!
$end
#10
1#
#20
1!
0#
1"
#30
1#
#40
0!
1$
0#
0"
#50
1!
1#
#60
0!
0#
1"
#70
1!
1#
